collective.portlet.discussion-2.0.0a2-py3.11-nspkg.pth
collective/portlet/discussion/__init__.py
collective/portlet/discussion/configure.zcml
collective/portlet/discussion/discussionportlet.pt
collective/portlet/discussion/discussionportlet.py
collective/portlet/discussion/i18n.sh
collective/portlet/discussion/testing.py
collective/portlet/discussion/upgrades.zcml
collective/portlet/discussion/browser/__init__.py
collective/portlet/discussion/browser/configure.zcml
collective/portlet/discussion/browser/discussion_list_search.pt
collective/portlet/discussion/browser/discussion_list_search.py
collective/portlet/discussion/locales/collective.portlet.discussion.pot
collective/portlet/discussion/locales/plone.pot
collective/portlet/discussion/locales/it/LC_MESSAGES/collective.portlet.discussion.mo
collective/portlet/discussion/locales/it/LC_MESSAGES/collective.portlet.discussion.po
collective/portlet/discussion/locales/it/LC_MESSAGES/plone.mo
collective/portlet/discussion/locales/it/LC_MESSAGES/plone.po
collective/portlet/discussion/locales/nl/LC_MESSAGES/collective.portlet.discussion.mo
collective/portlet/discussion/locales/nl/LC_MESSAGES/collective.portlet.discussion.po
collective/portlet/discussion/locales/nl/LC_MESSAGES/plone.mo
collective/portlet/discussion/locales/nl/LC_MESSAGES/plone.po
collective/portlet/discussion/profiles/default/metadata.xml
collective/portlet/discussion/profiles/default/portlets.xml
collective/portlet/discussion/profiles/uninstall/portlets.xml
collective/portlet/discussion/tests/__init__.py
collective/portlet/discussion/tests/test_portlet.py
collective/portlet/discussion/utility/__init__.py
collective/portlet/discussion/utility/configure.zcml
collective/portlet/discussion/utility/interfaces.py
collective/portlet/discussion/utility/utility.py
collective/portlet/discussion/utility/vocab.py
collective.portlet.discussion-2.0.0a2.dist-info/METADATA
collective.portlet.discussion-2.0.0a2.dist-info/WHEEL
collective.portlet.discussion-2.0.0a2.dist-info/entry_points.txt
collective.portlet.discussion-2.0.0a2.dist-info/namespace_packages.txt
collective.portlet.discussion-2.0.0a2.dist-info/top_level.txt
collective.portlet.discussion-2.0.0a2.dist-info/RECORD
