Metadata-Version: 2.1
Name: collective.portlet.discussion
Version: 2.0.0a2
Summary: A simple Plone portlet to show a list of comments
Home-page: https://github.com/collective/collective.portlet.discussion
Author: RedTurtle Technology
Author-email: sviluppoplone@redturtle.it
Maintainer: Maurits van Rees
Maintainer-email: m.van.rees@zestsoftware.nl
License: GPL
Keywords: discussion portlet comments
Classifier: Framework :: Plone
Classifier: Framework :: Plone :: 5.2
Classifier: Framework :: Plone :: 6.0
Classifier: Development Status :: 5 - Production/Stable
Classifier: License :: OSI Approved :: GNU General Public License v2 or later (GPLv2+)
Classifier: Programming Language :: Python
Classifier: Programming Language :: Python :: 2.7
Classifier: Programming Language :: Python :: 3.8
Classifier: Programming Language :: Python :: 3.9
Classifier: Programming Language :: Python :: 3.10
Classifier: Programming Language :: Python :: 3.11
Classifier: Topic :: Software Development :: Libraries :: Python Modules
Requires-Python: >=2.7,!=3.0.*,!=3.1.*,!=3.2.*,!=3.3.*,!=3.4.*,!=3.5.*
Requires-Dist: setuptools
Requires-Dist: plone.api
Requires-Dist: plone.app.discussion
Requires-Dist: six
Provides-Extra: test
Requires-Dist: plone.app.testing ; extra == 'test'
